moo/__init__.py
moo/moo.py
moo/xlos.py
moo_chem-0.0.1.dist-info/LICENSE
moo_chem-0.0.1.dist-info/METADATA
moo_chem-0.0.1.dist-info/WHEEL
moo_chem-0.0.1.dist-info/top_level.txt
moo_chem-0.0.1.dist-info/RECORD
